perplexity_advanced_mcp/__init__.py
perplexity_advanced_mcp/api_client.py
perplexity_advanced_mcp/cli.py
perplexity_advanced_mcp/config.py
perplexity_advanced_mcp/logging.py
perplexity_advanced_mcp/search_tool.py
perplexity_advanced_mcp/types.py
perplexity_advanced_mcp-0.1.3.dist-info/METADATA
perplexity_advanced_mcp-0.1.3.dist-info/WHEEL
perplexity_advanced_mcp-0.1.3.dist-info/entry_points.txt
perplexity_advanced_mcp-0.1.3.dist-info/RECORD
