Metadata-Version: 2.4
Name: perplexity-advanced-mcp
Version: 0.1.3
Summary: Advanced MCP tool for Perplexity and OpenRouter API integration. Supports both simple and complex queries with file attachments. Built with AI-first development approach using Cline, Cursor, and Wispr Flow.
Project-URL: Homepage, https://github.com/code-yeongyu/perplexity-advanced-mcp
Project-URL: Repository, https://github.com/code-yeongyu/perplexity-advanced-mcp.git
Project-URL: Bug Tracker, https://github.com/code-yeongyu/perplexity-advanced-mcp/issues
Author-email: YeonGyu Kim <public.kim.yeon.gyu@gmail.com>
License: MIT
Keywords: ai,claude,cline,cursor,llm,mcp,openrouter,perplexity,search
Classifier: Environment :: Console
Classifier: Intended Audience :: Developers
Classifier: License :: OSI Approved :: MIT License
Classifier: Operating System :: OS Independent
Classifier: Programming Language :: Python :: 3.12
Classifier: Topic :: Software Development :: Libraries :: Python Modules
Requires-Python: >=3.12
Requires-Dist: httpx>=0.28.1
Requires-Dist: mcp>=1.3.0
Requires-Dist: pydantic>=2.10.6
Requires-Dist: setuptools>=75.8.0
Requires-Dist: tenacity>=8.2.3
Requires-Dist: typer>=0.15.1
Provides-Extra: dev
Requires-Dist: mypy>=1.15.0; extra == 'dev'
Requires-Dist: ruff>=0.9.6; extra == 'dev'
